8-Bit Adder/full_adder.v
// Project name: "8bits_full_adder"
// Date of creation: "20.05.2024"
// Designer name: Youness Maarouf

// IDE name: "MS Code"
// Synthetizer Tool: "Icarus"
// Signal vizualisation Tool: "GTK Wave"


//Short description:
// Implement an 8 bits full adder, after a half adder has been implemented and simulated.
// The 8 bits full adder could also be visualized within (Digital Logic Sim from Sebastian Lague)
// https://sebastian.itch.io/digital-logic-sim


`timescale 1ms/1ps

module half_adder(in1, in2, sum, c);

    input in1, in2;
    output sum, c;

    xor (sum, in1, in2);
    and (c, in1, in2);

endmodule

module full_adder (A, B, C_in, Sum, C_out);

input A, B, C_in;
output Sum, C_out;

half_adder half_adder_st1 (.in1 (st1_in1), .in2 (st1_in2), .sum (st1_sum), .c (st1_c_out));

half_adder half_adder_st2 (.in1 (st2_in1), .in2 (st2_in2), .sum (st2_sum), .c (st2_c_out));

assign st1_in1 = A;
assign st1_in2 = B;

assign st2_in1 = C_in; // to be checked!!!!! checked and it works
assign st2_in2 = st1_sum;

assign Sum = st2_sum;

or (C_out, st1_c_out, st2_c_out);

endmodule

8-Bit Adder/full_adder_tb.v
`timescale 1ms/1ps
`include "full_adder.v"

module full_adder_tb;

reg full_a, full_b, full_c_in;
wire full_s, full_c_out;

full_adder uut(

    .A (full_a),
    .B (full_b),
    .C_in (full_c_in),
    .Sum (full_s),
    .C_out (full_c_out)
    );


  initial 
    begin

        $dumpfile("full_adder_tb.vcd");
        $dumpvars(0, full_adder_tb);

           full_a = 1'b0 ; full_b = 1'b0; full_c_in = 1'b0; 
        #1 full_a = 1'b0 ; full_b = 1'b0; full_c_in = 1'b1;
        #1 full_a = 1'b0 ; full_b = 1'b1; full_c_in = 1'b0;
        #1 full_a = 1'b0 ; full_b = 1'b1; full_c_in = 1'b1;
        #1 full_a = 1'b1 ; full_b = 1'b0; full_c_in = 1'b0;
        #1 full_a = 1'b1 ; full_b = 1'b0; full_c_in = 1'b1;
        #1 full_a = 1'b1 ; full_b = 1'b1; full_c_in = 1'b0;
        #1 full_a = 1'b1 ; full_b = 1'b1; full_c_in = 1'b1;


      $display("Test complete");
    end

  initial #8 $finish;


endmodule

8-Bit Adder/full_adder_tb.vcd
$date
	Mon May 20 23:50:28 2024
$end
$version
	Icarus Verilog
$end
$timescale
	1ps
$end
$scope module full_adder_tb $end
$var wire 1 ! full_s $end
$var wire 1 " full_c_out $end
$var reg 1 # full_a $end
$var reg 1 $ full_b $end
$var reg 1 % full_c_in $end
$scope module uut $end
$var wire 1 # A $end
$var wire 1 $ B $end
$var wire 1 % C_in $end
$var wire 1 " C_out $end
$var wire 1 ! Sum $end
$var wire 1 & st1_in1 $end
$var wire 1 ' st1_in2 $end
$var wire 1 ( st2_in1 $end
$var wire 1 ) st2_in2 $end
$var wire 1 * st2_sum $end
$var wire 1 + st2_c_out $end
$var wire 1 , st1_sum $end
$var wire 1 - st1_c_out $end
$scope module half_adder_st1 $end
$var wire 1 - c $end
$var wire 1 & in1 $end
$var wire 1 ' in2 $end
$var wire 1 , sum $end
$upscope $end
$scope module half_adder_st2 $end
$var wire 1 + c $end
$var wire 1 ( in1 $end
$var wire 1 ) in2 $end
$var wire 1 * sum $end
$upscope $end
$upscope $end
$upscope $end
$enddefinitions $end
$comment Show the parameter values. $end
$dumpall
$end
#0
$dumpvars
0-
0,
0+
0*
0)
0(
0'
0&
0%
0$
0#
0"
0!
$end
#1000000000
1!
1*
1(
1%
#2000000000
1)
1,
0(
0%
1'
1$
#3000000000
1"
0!
0*
1+
1(
1%
#4000000000
0"
1!
1*
0+
0(
0%
0'
0$
1&
1#
#5000000000
1"
0!
0*
1+
1(
1%
#6000000000
0+
0)
0,
1-
0(
0%
1'
1$
#7000000000
1!
1*
1(
1%
