8-Bit Adder/half_adder.v
`timescale 1ns/1ps

// module half_adder(half_a, half_b,s,c);
//     input half_a, half_b;
//     output s, c;
//     xor (s, half_a, half_b);
//     and (c, half_a, half_b);
// endmodule

module half_adder(HA_in1, HA_in2, HA_sum, HA_cout);

    input HA_in1, HA_in2;
    output HA_sum, HA_cout;

    xor (HA_sum, HA_in1, HA_in2);
    and (HA_cout, HA_in1, HA_in2);

endmodule

8-Bit Adder/src/full_adder.v
// Project name: "8bits_full_adder"
// Date of creation: "20.05.2024"
// Designer name: Youness Maarouf

// IDE name: "MS Code"
// Synthetizer Tool: "Icarus"
// Signal vizualisation Tool: "GTK Wave"


//Short description:
// Implement an 8 bits full adder, after a half adder has been implemented and simulated.
// The 8 bits full adder could also be visualized within (Digital Logic Sim from Sebastian Lague)
// https://sebastian.itch.io/digital-logic-sim


`timescale 1ms/1ps
`include "half_adder.v"

// module half_adder(HA_in1, HA_in2, HA_sum, HA_cout);

//     input HA_in1, HA_in2;
//     output HA_sum, HA_cout;

//     xor (sum, HA_in1, HA_in2);
//     and (HA_cout, HA_in1, HA_in2);

// endmodule

module full_adder (FA_in1, FA_in2, FA_cin, FA_sum, FA_cout);

input FA_in1, FA_in2, FA_cin;
output FA_sum, FA_cout;

half_adder half_adder_st1 (.HA_in1 (st1_HA_in1), .HA_in2 (st1_HA_in2), .HA_sum (st1_sum), .HA_cout (st1_c_out));

half_adder half_adder_st2 (.HA_in1 (st2_HA_in1), .HA_in2 (st2_HA_in2), .HA_sum (st2_sum), .HA_cout (st2_c_out));

assign st1_HA_in1 = FA_in1;
assign st1_HA_in2 = FA_in2;

assign st2_HA_in1 = FA_cin; // to be checked!!!!! checked and it works
assign st2_HA_in2 = st1_sum;

assign FA_sum = st2_sum;

or (FA_cout, st1_c_out, st2_c_out);

endmodule

8-Bit Adder/tb_full_adder.v
`timescale 1ms/1ps
`include "full_adder.v"

module tb_full_adder;

reg tb_FA_in1, tb_FA_in2, tb_FA_cin;
wire tb_FA_sum, tb_FA_cout;

full_adder uut(

    .FA_in1 (tb_FA_in1),
    .FA_in2 (tb_FA_in2),
    .FA_cin (tb_FA_cin),
    .FA_sum (tb_FA_sum),
    .FA_cout (tb_FA_cout)
    );

  initial 
    begin

        $dumpfile("tb_full_adder.vcd");
        $dumpvars(0, tb_full_adder);

           tb_FA_in1 = 1'b0 ; tb_FA_in2 = 1'b0; tb_FA_cin = 1'b0; 
        #1 tb_FA_in1 = 1'b0 ; tb_FA_in2 = 1'b0; tb_FA_cin = 1'b1;
        #1 tb_FA_in1 = 1'b0 ; tb_FA_in2 = 1'b1; tb_FA_cin = 1'b0;
        #1 tb_FA_in1 = 1'b0 ; tb_FA_in2 = 1'b1; tb_FA_cin = 1'b1;
        #1 tb_FA_in1 = 1'b1 ; tb_FA_in2 = 1'b0; tb_FA_cin = 1'b0;
        #1 tb_FA_in1 = 1'b1 ; tb_FA_in2 = 1'b0; tb_FA_cin = 1'b1;
        #1 tb_FA_in1 = 1'b1 ; tb_FA_in2 = 1'b1; tb_FA_cin = 1'b0;
        #1 tb_FA_in1 = 1'b1 ; tb_FA_in2 = 1'b1; tb_FA_cin = 1'b1;


      $display("Test complete");
    end

  initial #8 $finish;


endmodule

8-Bit Adder/tb_full_adder.vcd
$date
	Thu May 23 12:21:37 2024
$end
$version
	Icarus Verilog
$end
$timescale
	1ps
$end
$scope module tb_full_adder $end
$var wire 1 ! tb_FA_sum $end
$var wire 1 " tb_FA_cout $end
$var reg 1 # tb_FA_cin $end
$var reg 1 $ tb_FA_in1 $end
$var reg 1 % tb_FA_in2 $end
$scope module uut $end
$var wire 1 # FA_cin $end
$var wire 1 " FA_cout $end
$var wire 1 $ FA_in1 $end
$var wire 1 % FA_in2 $end
$var wire 1 ! FA_sum $end
$var wire 1 & st1_HA_in1 $end
$var wire 1 ' st1_HA_in2 $end
$var wire 1 ( st2_HA_in1 $end
$var wire 1 ) st2_HA_in2 $end
$var wire 1 * st2_sum $end
$var wire 1 + st2_c_out $end
$var wire 1 , st1_sum $end
$var wire 1 - st1_c_out $end
$scope module half_adder_st1 $end
$var wire 1 - HA_cout $end
$var wire 1 & HA_in1 $end
$var wire 1 ' HA_in2 $end
$var wire 1 , HA_sum $end
$upscope $end
$scope module half_adder_st2 $end
$var wire 1 + HA_cout $end
$var wire 1 ( HA_in1 $end
$var wire 1 ) HA_in2 $end
$var wire 1 * HA_sum $end
$upscope $end
$upscope $end
$upscope $end
$enddefinitions $end
$comment Show the parameter values. $end
$dumpall
$end
#0
$dumpvars
0-
0,
0+
0*
0)
0(
0'
0&
0%
0$
0#
0"
0!
$end
#1000
1!
1*
1(
1#
#2000
1)
1,
0(
0#
1'
1%
#3000
1"
0!
0*
1+
1(
1#
#4000
0"
1!
1*
0+
0(
0#
0'
0%
1&
1$
#5000
1"
0!
0*
1+
1(
1#
#6000
0+
0)
0,
1-
0(
0#
1'
1%
#7000
1!
1*
1(
1#
